Metadata-Version: 2.1
Name: pyDoujinshiInfo
Version: 0.1.0.5
Summary: Unofficial API wrapper for doujinshi.info
Home-page: https://github.com/layolu/pyDoujinshiInfo
Author: layolu layole
Author-email: layolulayole@gmail.com
License: Apache 2.0
Keywords: doujinshi,api-wrapper,rest-api-wrapper,python3
Platform: UNKNOWN
